{
  "label": "Popularity = Low", "condition": "0.50", "type": "split", "leaf_num": "100", "sample_count": "0",
  "children": [
    {
      "label": "Day <= Monday", "condition": "1.50", "type": "split", "leaf_num": "100", "sample_count": "0",
      "children": [
        {
          "label": "Leaf - 2", "condition": 0, "type": "leaf", "leaf_num": "2", "sample_count": "33"}, {
          "label": "Day <= Thursday", "condition": "4.50", "type": "split", "leaf_num": "100", "sample_count": "0",
          "children": [
            {
              "label": "Leaf - 4", "condition": 0, "type": "leaf", "leaf_num": "4", "sample_count": "190"}, {
              "label": "Leaf - 5", "condition": 0, "type": "leaf", "leaf_num": "5", "sample_count": "45"}]}]}, {
      "label": "Day <= Thursday", "condition": "4.50", "type": "split", "leaf_num": "100", "sample_count": "0",
      "children": [
        {
          "label": "Day <= Monday", "condition": "1.50", "type": "split", "leaf_num": "100", "sample_count": "0",
          "children": [
            {
              "label": "Leaf - 8", "condition": 0, "type": "leaf", "leaf_num": "8", "sample_count": "206"}, {
              "label": "Leaf - 9", "condition": 0, "type": "leaf", "leaf_num": "9", "sample_count": "846"}]}, {
          "label": "Popularity = Low/Medium", "condition": "1.50", "type": "split", "leaf_num": "100", "sample_count": "0",
          "children": [
            {
              "label": "Leaf - 11", "condition": 0, "type": "leaf", "leaf_num": "11", "sample_count": "59"}, {
              "label": "Leaf - 12", "condition": 0, "type": "leaf", "leaf_num": "12", "sample_count": "177"}]}]}]}
